fact_worthiness/__init__.py
fact_worthiness/fact_worthy.py
fact_worthiness/keyword_check.py
fact_worthiness/len_check.py
fact_worthiness/ml_check.py
fact_worthiness/ner_check.py
fact_filtering-0.1.1.dist-info/METADATA
fact_filtering-0.1.1.dist-info/WHEEL
fact_filtering-0.1.1.dist-info/entry_points.txt
fact_filtering-0.1.1.dist-info/top_level.txt
fact_filtering-0.1.1.dist-info/RECORD
